sphinxcontrib/email/__init__.py
sphinxcontrib/email/handlers.py
sphinxcontrib/email/roles.py
sphinxcontrib/email/utils.py
sphinxcontrib_email-0.3.6.dist-info/LICENSE
sphinxcontrib_email-0.3.6.dist-info/METADATA
sphinxcontrib_email-0.3.6.dist-info/WHEEL
sphinxcontrib_email-0.3.6.dist-info/top_level.txt
sphinxcontrib_email-0.3.6.dist-info/RECORD
