Metadata-Version: 2.1
Name: sphinxcontrib-email
Version: 0.3.6
Summary: Sphinx email obfuscation extension
Home-page: https://github.com/sphinx-contrib/email
Download-URL: http://pypi.python.org/pypi/sphinxcontrib-email
Author: Christian Knittl-Frank
Author-email: lcnittl@gmail.com
License: BSD-3-Clause
Project-URL: GitHub: repo, https://github.com/sphinx-contrib/email
Project-URL: GitHub: issues, https://github.com/sphinx-contrib/email/issues
Classifier: Development Status :: 3 - Alpha
Classifier: Environment :: Console
Classifier: Environment :: Web Environment
Classifier: Framework :: Sphinx :: Extension
Classifier: Intended Audience :: Developers
Classifier: License :: OSI Approved :: BSD License
Classifier: Operating System :: OS Independent
Classifier: Programming Language :: Python :: 3
Classifier: Programming Language :: Python :: 3 :: Only
Classifier: Topic :: Documentation :: Sphinx
Classifier: Topic :: Utilities
Requires-Python: >=3.7
License-File: LICENSE
Requires-Dist: Sphinx (>=1.8)
Requires-Dist: lxml (>=4.5.2)
